langchain_vercel_adapters/__init__.py
langchain_vercel_adapters/types.py
langchain_vercel_adapters/stream_protocol/data_stream.py
langchain_vercel_adapters-0.1.0.dist-info/METADATA
langchain_vercel_adapters-0.1.0.dist-info/WHEEL
langchain_vercel_adapters-0.1.0.dist-info/licenses/LICENCE
langchain_vercel_adapters-0.1.0.dist-info/RECORD
