Metadata-Version: 2.4
Name: langchain-vercel-adapters
Version: 0.1.0
Summary: Add your description here
Project-URL: Homepage, https://github.com/reveal-hub/langchain-vercel-adapters
License-File: LICENCE
Requires-Python: <4.0,>=3.10
Requires-Dist: langchain<0.4.0,>=0.3.25
Requires-Dist: pydantic<3.0.0,>=2.11.4
